batfish/__about__.py
batfish/cli.py
batfish/__init__.py
batfish/console.py
batfish/client.py
batfish/models/region.py
batfish/models/action.py
batfish/models/image.py
batfish/models/__init__.py
batfish/models/droplet.py
batfish/models/size.py
batfish-0.0.2.dist-info/zip-safe
batfish-0.0.2.dist-info/DESCRIPTION.rst
batfish-0.0.2.dist-info/RECORD
batfish-0.0.2.dist-info/entry_points.txt
batfish-0.0.2.dist-info/METADATA
batfish-0.0.2.dist-info/metadata.json
batfish-0.0.2.dist-info/WHEEL
batfish-0.0.2.dist-info/top_level.txt
tests/test_client.py
tests/test_token.py
tests/__init__.py
