Metadata-Version: 2.0
Name: batfish
Version: 0.0.2
Summary: A DigitalOcean shell, API and CLI interface
Home-page: https://batfish.readthedocs.org/
Author: Kura
Author-email: kura@kura.io
License: MIT
Keywords: digital,ocean,shell,cli
Platform: linux
Classifier: Development Status :: 4 - Beta
Classifier: Intended Audience :: Developers
Classifier: Natural Language :: English
Classifier: License :: OSI Approved :: MIT License
Classifier: Programming Language :: Python
Classifier: Programming Language :: Python :: 2.6
Classifier: Programming Language :: Python :: 2.7
Classifier: Programming Language :: Python :: 3
Classifier: Programming Language :: Python :: 3.3
Classifier: Programming Language :: Python :: 3.4
Classifier: Programming Language :: Python :: Implementation :: CPython
Classifier: Programming Language :: Python :: Implementation :: PyPy
Classifier: Topic :: Software Development :: Libraries :: Python Modules
Classifier: Topic :: System :: Archiving :: Packaging
Requires: requests
Requires: click
Provides: batfish
Requires-Dist: requests
Requires-Dist: click
